<Languages>
    <category>
        <name>German</name>
        <dateCreated>2024-05-12</dateCreated>
        <dateUpdated></dateUpdated>
        <status>true</status>
    </category>
    <category>
        <name>English</name>
        <dateCreated>2024-05-12</dateCreated>
        <dateUpdated></dateUpdated>
        <status>true</status>
    </category>
    <category>
        <name>Filipino</name>
        <dateCreated>2024-05-12</dateCreated>
        <dateUpdated></dateUpdated>
        <status>true</status>
    </category>
</Languages>